numero_fun/__init__.py
numero_fun/calculator.py
numero_fun/cli.py
numero_fun-0.1.2.dist-info/licenses/LICENSE
numero_fun-0.1.2.dist-info/licenses/LICENSE_HEADER
numero_fun-0.1.2.dist-info/METADATA
numero_fun-0.1.2.dist-info/WHEEL
numero_fun-0.1.2.dist-info/entry_points.txt
numero_fun-0.1.2.dist-info/top_level.txt
numero_fun-0.1.2.dist-info/RECORD
