Metadata-Version: 2.4
Name: numero-fun
Version: 0.1.2
Summary: A CLI tool for calculating numerology of names
Author: Garima Shrivastava
License: GPL-3.0
Project-URL: Homepage, https://github.com/techy4shri/Numero-Fun
Project-URL: Issues, https://github.com/techy4shri/Numero-Fun/issues
Keywords: numerology,cli,calculator
Classifier: Programming Language :: Python :: 3
Classifier: License :: OSI Approved :: GNU General Public License v3 (GPLv3)
Classifier: Operating System :: OS Independent
Classifier: Environment :: Console
Requires-Python: >=3.8
License-File: LICENSE
License-File: LICENSE_HEADER
Requires-Dist: rich>=13.0.0
Requires-Dist: questionary>=1.10.0
Provides-Extra: dev
Requires-Dist: pytest>=7.0; extra == "dev"
Requires-Dist: black>=23.0; extra == "dev"
Requires-Dist: flake8>=6.0; extra == "dev"
Requires-Dist: build>=0.7.0; extra == "dev"
Requires-Dist: twine>=4.0.0; extra == "dev"
Dynamic: license-file
